thorlabs_apt_device/__init__.py
thorlabs_apt_device/enums.py
thorlabs_apt_device/utils.py
thorlabs_apt_device/devices/__init__.py
thorlabs_apt_device/devices/aptdevice.py
thorlabs_apt_device/devices/aptdevice_motor.py
thorlabs_apt_device/devices/bbd.py
thorlabs_apt_device/devices/bsc.py
thorlabs_apt_device/devices/kdc101.py
thorlabs_apt_device/devices/tdc001.py
thorlabs_apt_device/protocol/__init__.py
thorlabs_apt_device/protocol/functions.py
thorlabs_apt_device/protocol/parsing.py
thorlabs_apt_device/protocol/unpacker.py
thorlabs_apt_device-0.3.8.dist-info/LICENSE
thorlabs_apt_device-0.3.8.dist-info/METADATA
thorlabs_apt_device-0.3.8.dist-info/WHEEL
thorlabs_apt_device-0.3.8.dist-info/top_level.txt
thorlabs_apt_device-0.3.8.dist-info/RECORD
