Metadata-Version: 2.1
Name: thorlabs-apt-device
Version: 0.3.8
Summary: Interface to ThorLabs devices which communicate using the APT protocol.
Home-page: https://gitlab.com/ptapping/thorlabs-apt-device
Author: Patrick Tapping
Author-email: mail@patricktapping.com
License: UNKNOWN
Project-URL: Documentation, https://thorlabs-apt-device.readthedocs.io/
Project-URL: Source, https://gitlab.com/ptapping/thorlabs-apt-device
Project-URL: Tracker, https://gitlab.com/ptapping/thorlabs-apt-device/-/issues
Platform: UNKNOWN
Classifier: Programming Language :: Python :: 3
Classifier: License :: OSI Approved :: GNU General Public License v3 or later (GPLv3+)
Classifier: Operating System :: OS Independent
Requires-Python: >=3.6
License-File: LICENSE
